<?xml version="1.0"?>
<clickhouse replace="true">
    <profiles>
        <default>
            <max_memory_usage>10000000000</max_memory_usage>
            <use_uncompressed_cache>1</use_uncompressed_cache>
            <async_insert>1</async_insert>
            <wait_for_async_insert>1</wait_for_async_insert>
            <min_insert_block_size_rows>1572673</min_insert_block_size_rows>
            <min_insert_block_size_bytes>536805888</min_insert_block_size_bytes>
            <receive_timeout>300</receive_timeout>
            <send_timeout>300</send_timeout>
            <receive_data_timeout_ms>0</receive_data_timeout_ms>
            <load_balancing>in_order</load_balancing>
            <log_queries>1</log_queries>
            <http_receive_timeout>120</http_receive_timeout>
            <http_send_timeout>120</http_send_timeout>
            <max_insert_threads>5</max_insert_threads>
        </default>
    </profiles>
    <users>
        <default>
            <access_management>1</access_management>
            <profile>default</profile>
            <networks>
                <ip>::/0</ip>
            </networks>
            <quota>default</quota>
            <access_management>1</access_management>
            <named_collection_control>1</named_collection_control>
            <show_named_collections>1</show_named_collections>
            <show_named_collections_secrets>1</show_named_collections_secrets>
            <password></password>
        </default>
        <read>
            <access_management>1</access_management>
            <password>q2QDQ8U4r45nbSfK</password>
            <networks incl="networks" replace="replace">
                <ip>::/0</ip>
            </networks>
            <profile>default</profile>
            <quota>default</quota>
        </read>
        <admin>
            <password>ekJvUF4p2MuUC433</password>
            <access_management>1</access_management>
            <networks incl="networks" replace="replace">
                <ip>::/0</ip>
            </networks>
            <profile>default</profile>
            <quota>default</quota>
            <access_management>1</access_management>
            <named_collection_control>1</named_collection_control>
            <show_named_collections>1</show_named_collections>
            <show_named_collections_secrets>1</show_named_collections_secrets>
        </admin>
    </users>
    <quotas>
        <default>
            <interval>
                <duration>3600</duration>
                <queries>0</queries>
                <errors>0</errors>
                <result_rows>0</result_rows>
                <read_rows>0</read_rows>
                <execution_time>0</execution_time>
            </interval>
        </default>
    </quotas>
</clickhouse>
